.browserslistrc
tsconfig.json
betty/__init__.py
betty/_bootstrap.py
betty/_npm.py
betty/about.py
betty/assets.py
betty/asyncio.py
betty/concurrent.py
betty/date.py
betty/deriver.py
betty/docstring.py
betty/documentation.py
betty/error.py
betty/event_dispatcher.py
betty/factory.py
betty/fs.py
betty/functools.py
betty/hashid.py
betty/image.py
betty/importlib.py
betty/job.py
betty/link.py
betty/machine_name.py
betty/multiprocessing.py
betty/mutability.py
betty/openapi.py
betty/os.py
betty/py.typed
betty/render.py
betty/repr.py
betty/requirement.py
betty/serve.py
betty/service.py
betty/string.py
betty/subprocess.py
betty/typing.py
betty/user.py
betty/warnings.py
betty/ancestry/__init__.py
betty/ancestry/citation.py
betty/ancestry/date.py
betty/ancestry/description.py
betty/ancestry/enclosure.py
betty/ancestry/event.py
betty/ancestry/file.py
betty/ancestry/file_reference.py
betty/ancestry/has_citations.py
betty/ancestry/has_file_references.py
betty/ancestry/has_notes.py
betty/ancestry/link.py
betty/ancestry/locale.py
betty/ancestry/media_type.py
betty/ancestry/name.py
betty/ancestry/note.py
betty/ancestry/person.py
betty/ancestry/person_name.py
betty/ancestry/place.py
betty/ancestry/presence.py
betty/ancestry/source.py
betty/ancestry/event_type/__init__.py
betty/ancestry/event_type/event_types.py
betty/ancestry/gender/__init__.py
betty/ancestry/gender/genders.py
betty/ancestry/place_type/__init__.py
betty/ancestry/place_type/place_types.py
betty/ancestry/presence_role/__init__.py
betty/ancestry/presence_role/presence_roles.py
betty/app/__init__.py
betty/app/config.py
betty/app/factory.py
betty/assertion/__init__.py
betty/assertion/error.py
betty/assets/locale/betty.pot
betty/assets/locale/ar/betty.po
betty/assets/locale/de-DE/betty.po
betty/assets/locale/en-GB/betty.po
betty/assets/locale/es-ES/betty.po
betty/assets/locale/fr-FR/betty.po
betty/assets/locale/he/betty.po
betty/assets/locale/nl-NL/betty.po
betty/assets/locale/pt-BR/betty.po
betty-0.4.37.dist-info/licenses/LICENSE.txt
betty-0.4.37.dist-info/METADATA
betty-0.4.37.dist-info/WHEEL
betty-0.4.37.dist-info/entry_points.txt
betty-0.4.37.dist-info/top_level.txt
betty-0.4.37.dist-info/RECORD
