Metadata-Version: 2.4
Name: betty
Version: 0.4.37
Summary: Betty visualizes and publishes your family history by building interactive, encyclopedia-like genealogy websites out of your Gramps and GEDCOM family trees
Author-email: Bart Feenstra <bar@bartfeenstra.com>
License: GNU GENERAL PUBLIC LICENSE
Project-URL: Documentation, https://betty.readthedocs.io
Project-URL: GitHub, https://github.com/bartfeenstra/betty
Classifier: Environment :: Console
Classifier: Intended Audience :: Developers
Classifier: Intended Audience :: End Users/Desktop
Classifier: Intended Audience :: Science/Research
Classifier: License :: OSI Approved :: GNU General Public License v3 or later (GPLv3+)
Classifier: Programming Language :: JavaScript
Classifier: Programming Language :: Python :: 3.11
Classifier: Programming Language :: Python :: 3.12
Classifier: Programming Language :: Python :: 3.13
Classifier: Programming Language :: Python :: 3.14
Classifier: Programming Language :: Unix Shell
Classifier: Operating System :: MacOS :: MacOS X
Classifier: Operating System :: POSIX :: Linux
Classifier: Operating System :: Microsoft :: Windows
Classifier: Topic :: Internet
Classifier: Topic :: Scientific/Engineering :: Visualization
Classifier: Topic :: Sociology :: Genealogy
Classifier: Topic :: Sociology :: History
Classifier: Topic :: Software Development :: Code Generators
Classifier: Natural Language :: Arabic
Classifier: Natural Language :: Dutch
Classifier: Natural Language :: English
Classifier: Natural Language :: French
Classifier: Natural Language :: German
Classifier: Natural Language :: Hebrew
Classifier: Natural Language :: Russian
Classifier: Natural Language :: Ukrainian
Classifier: Typing :: Typed
Requires-Python: ~=3.11
License-File: LICENSE.txt
Requires-Dist: aiofiles~=24.1
Requires-Dist: aiohttp~=3.10
Requires-Dist: asyncclick~=8.2
Requires-Dist: babel~=2.16
Requires-Dist: furo==2025.7.19
Requires-Dist: geopy~=2.4
Requires-Dist: html5lib~=1.1
Requires-Dist: jinja2~=3.1
Requires-Dist: jsonschema~=4.23
Requires-Dist: langcodes~=3.4
Requires-Dist: lxml~=6.0
Requires-Dist: markupsafe~=3.0
Requires-Dist: multidict~=6.1
Requires-Dist: pdf2image~=1.17
Requires-Dist: polib~=1.2
Requires-Dist: Pillow~=11.0
Requires-Dist: pyyaml~=6.0
Requires-Dist: referencing~=0.36.2
Requires-Dist: sphinx~=8.1
Requires-Dist: sphinx-design~=0.6.1
Requires-Dist: typing_extensions~=4.12
Provides-Extra: setuptools
Requires-Dist: build~=1.2.2; extra == "setuptools"
Requires-Dist: twine~=6.0; extra == "setuptools"
Requires-Dist: wheel~=0.44; extra == "setuptools"
Provides-Extra: test
Requires-Dist: aioresponses~=0.7; extra == "test"
Requires-Dist: basedmypy~=2.6; extra == "test"
Requires-Dist: coverage~=7.6; extra == "test"
Requires-Dist: packaging~=25.0; extra == "test"
Requires-Dist: puremagic~=1.28; extra == "test"
Requires-Dist: pytest~=8.3; extra == "test"
Requires-Dist: pytest-aioresponses~=0.2; extra == "test"
Requires-Dist: pytest-asyncio~=1.0; extra == "test"
Requires-Dist: pytest-mock~=3.14; extra == "test"
Requires-Dist: pytest-playwright-asyncio~=0.7; extra == "test"
Requires-Dist: requests~=2.32; extra == "test"
Requires-Dist: ruff~=0.11; extra == "test"
Requires-Dist: types-aiofiles~=24.1; extra == "test"
Requires-Dist: types-babel~=2.11; extra == "test"
Requires-Dist: types-html5lib~=1.1; extra == "test"
Requires-Dist: types-jsonschema~=4.23; extra == "test"
Requires-Dist: types-lxml>=2024.9.16; extra == "test"
Requires-Dist: types-polib~=1.2; extra == "test"
Requires-Dist: types-pyyaml~=6.0; extra == "test"
Requires-Dist: types-requests~=2.32; extra == "test"
Requires-Dist: types-setuptools~=80.0; extra == "test"
Requires-Dist: virtualenv~=20.27; extra == "test"
Requires-Dist: betty[setuptools]; extra == "test"
Provides-Extra: development
Requires-Dist: pytest-repeat~=0.9; extra == "development"
Requires-Dist: betty[test]; extra == "development"
Provides-Extra: ci
Requires-Dist: codecov~=2.1; extra == "ci"
Requires-Dist: betty[test]; extra == "ci"
Dynamic: license-file
